atomicpuppy/__init__.py
atomicpuppy/__init__.pyi
atomicpuppy/_version.py
atomicpuppy/atomicpuppy.py
atomicpuppy/errors.py
atomicpuppy/errors.pyi
atomicpuppy/py.typed
tests/__init__.py
tests/fakehttp.py
tests/fakes.py
tests/test_atomicpuppy.py
tests/test_dispatching.py
tests/test_event.py
tests/test_fetching.py
tests/test_posting.py
tests/test_redis_event_counter.py
tests/test_stream_config.py
AtomicPuppy-1.5.6.dist-info/LICENSE
AtomicPuppy-1.5.6.dist-info/METADATA
AtomicPuppy-1.5.6.dist-info/WHEEL
AtomicPuppy-1.5.6.dist-info/top_level.txt
AtomicPuppy-1.5.6.dist-info/RECORD
