Metadata-Version: 2.1
Name: AtomicPuppy
Version: 1.5.6
Summary: A service-activator component for eventstore
Home-page: https://github.com/madedotcom/atomicpuppy
Author: Bob Gregory
Author-email: bob@made.com
License: MIT
Keywords: eventstore
License-File: LICENSE
Requires-Dist: aiohttp
Requires-Dist: chardet
Requires-Dist: gevent
Requires-Dist: pybreaker
Requires-Dist: PyYAML
Requires-Dist: redis
Requires-Dist: retrying
Requires-Dist: requests
